ledmx/__init__.py
ledmx/layout.py
ledmx/model.py
ledmx/multiverse.py
ledmx/transport.py
ledmx/utils.py
ledmx/artnet/__init__.py
ledmx/artnet/packet.py
ledmx/artnet/tests/__init__.py
ledmx/artnet/tests/test_packet.py
ledmx/tests/__init__.py
ledmx/tests/test_layout.py
ledmx/tests/test_multiverse.py
ledmx/tests/test_utils.py
ledmx-0.2a0.dist-info/METADATA
ledmx-0.2a0.dist-info/WHEEL
ledmx-0.2a0.dist-info/top_level.txt
ledmx-0.2a0.dist-info/RECORD
