Metadata-Version: 2.1
Name: ledmx
Version: 0.2a0
Summary: ArtDMX Multiverse lib
Home-page: https://github.com/mserg/ledmx-lib
Author: Sergei Michenko
Author-email: mserg@tih.ru
License: MIT
Classifier: Programming Language :: Python :: 3
Classifier: License :: OSI Approved :: MIT License
Requires-Python: >=3.10
Requires-Dist: pytest
Requires-Dist: PyYAML
Requires-Dist: numpy
Requires-Dist: mock
Requires-Dist: schema
